resize_right/__init__.py
resize_right/resize_right.py
resize_right-0.0.1.dist-info/LICENSE
resize_right-0.0.1.dist-info/METADATA
resize_right-0.0.1.dist-info/WHEEL
resize_right-0.0.1.dist-info/top_level.txt
resize_right-0.0.1.dist-info/RECORD
