Metadata-Version: 2.1
Name: resize-right
Version: 0.0.1
Summary: Resize Right
Home-page: https://github.com/assafshocher/ResizeRight
Author: Assaf Shocher
Author-email: assafshocher@gmail.com
License: MIT
Keywords: deep learning,image resize
Platform: UNKNOWN
Classifier: Development Status :: 4 - Beta
Classifier: Intended Audience :: Developers
Classifier: Topic :: Scientific/Engineering :: Artificial Intelligence
Classifier: License :: OSI Approved :: MIT License
Classifier: Programming Language :: Python :: 3.6
License-File: LICENSE
